spinOps/spinOps.cpython-39-darwin.so
spinOps-0.1.1.dist-info/METADATA
spinOps-0.1.1.dist-info/WHEEL
spinOps-0.1.1.dist-info/top_level.txt
spinOps-0.1.1.dist-info/RECORD
