Metadata-Version: 2.1
Name: spinOps
Version: 0.1.1
Summary: A Python package for spin operations
Home-page: https://github.com/pjgrandinetti/spinOps
Author: Philip J. Grandinetti
Author-email: grandinetti.1@osu.edu
Classifier: Development Status :: 3 - Alpha
Classifier: Intended Audience :: Developers
Classifier: License :: OSI Approved :: MIT License
Classifier: Programming Language :: Python :: 3.6
Classifier: Programming Language :: Python :: 3.7
Classifier: Programming Language :: Python :: 3.8
Classifier: Programming Language :: Python :: 3.9
